{"namedChunkGroups":{"polyfill":{"name":"polyfill","assets":[{"name":"webpack-runtime-128f6157c18dfc6925f8.js","size":4287},{"name":"polyfill-d5b166f0a6e4a874141e.js","size":82637}],"filteredAssets":0,"assetsSize":86924,"filteredAuxiliaryAssets":2,"auxiliaryAssetsSize":218770},"app":{"name":"app","assets":[{"name":"webpack-runtime-128f6157c18dfc6925f8.js","size":4287},{"name":"framework-1484e8f4891ab3076b81.js","size":129929},{"name":"app-4aa4e71b520e3167bc6e.js","size":50726}],"filteredAssets":0,"assetsSize":184942,"filteredAuxiliaryAssets":3,"auxiliaryAssetsSize":547962},"component---src-pages-404-js":{"name":"component---src-pages-404-js","assets":[{"name":"component---src-pages-404-js-95612a61147e5b4daf40.js","size":814}],"filteredAssets":0,"assetsSize":814,"filteredAuxiliaryAssets":1,"auxiliaryAssetsSize":1888},"component---src-pages-index-tsx":{"name":"component---src-pages-index-tsx","assets":[{"name":"styles.1ced779e8f647de6e6c6.css","size":118},{"name":"component---src-pages-index-tsx-48b025208f47de56d683.js","size":166353}],"filteredAssets":0,"assetsSize":166471,"filteredAuxiliaryAssets":5,"auxiliaryAssetsSize":17897040}},"assetsByChunkName":{"polyfill":["webpack-runtime-128f6157c18dfc6925f8.js","polyfill-d5b166f0a6e4a874141e.js"],"app":["webpack-runtime-128f6157c18dfc6925f8.js","framework-1484e8f4891ab3076b81.js","app-4aa4e71b520e3167bc6e.js"],"component---src-pages-404-js":["component---src-pages-404-js-95612a61147e5b4daf40.js"],"component---src-pages-index-tsx":["styles.1ced779e8f647de6e6c6.css","component---src-pages-index-tsx-48b025208f47de56d683.js"]},"childAssetsByChunkName":{}}